Classfile /home/subaochen/git/blog/src/java/Person.class
  Last modified 2018年12月2日; size 310 bytes
  MD5 checksum 3f24365f1557571a81fb3369533d20ee
  Compiled from "Person.java"
public class Person
  minor version: 0
  major version: 55
  flags: (0x0021) ACC_PUBLIC, ACC_SUPER
  this_class: #3                          // Person
  super_class: #4                         // java/lang/Object
  interfaces: 0, fields: 1, methods: 2, attributes: 1
Constant pool:
   #1 = Methodref          #4.#16         // java/lang/Object."<init>":()V
   #2 = Fieldref           #3.#17         // Person.age:I
   #3 = Class              #18            // Person
   #4 = Class              #19            // java/lang/Object
   #5 = Utf8               age
   #6 = Utf8               I
   #7 = Utf8               <init>
   #8 = Utf8               ()V
   #9 = Utf8               Code
  #10 = Utf8               LineNumberTable
  #11 = Utf8               isAdult
  #12 = Utf8               ()Z
  #13 = Utf8               StackMapTable
  #14 = Utf8               SourceFile
  #15 = Utf8               Person.java
  #16 = NameAndType        #7:#8          // "<init>":()V
  #17 = NameAndType        #5:#6          // age:I
  #18 = Utf8               Person
  #19 = Utf8               java/lang/Object
{
  public Person();
    descriptor: ()V
    flags: (0x0001) ACC_PUBLIC
    Code:
      stack=1, locals=1, args_size=1
         0: aload_0
         1: invokespecial #1                  // Method java/lang/Object."<init>":()V
         4: return
      LineNumberTable:
        line 1: 0

  public boolean isAdult();
    descriptor: ()Z
    flags: (0x0001) ACC_PUBLIC
    Code:
      stack=2, locals=1, args_size=1
         0: aload_0
         1: getfield      #2                  // Field age:I
         4: bipush        18
         6: if_icmple     13
         9: iconst_1
        10: goto          14
        13: iconst_0
        14: ireturn
      LineNumberTable:
        line 5: 0
      StackMapTable: number_of_entries = 2
        frame_type = 13 /* same */
        frame_type = 64 /* same_locals_1_stack_item */
          stack = [ int ]
}
SourceFile: "Person.java"
